build/lib/yindd/yindd.py
yinddt/__init__.py
yinddt/yindd.py
yindd2-1.0.0.dist-info/METADATA
yindd2-1.0.0.dist-info/WHEEL
yindd2-1.0.0.dist-info/top_level.txt
yindd2-1.0.0.dist-info/RECORD
