Metadata-Version: 2.1
Name: yindd2
Version: 1.0.0
Summary: jwt
Author: Dada.cod
Author-email: 1078515202@qq.com
License: MIT
Keywords: jwt_f
